{
    "name": "Howdy",
    "panels": [
        {
            "width": 7,
            "height": 2,
            "actions": [
                {
                    "key": "a",
                    "x": 0,
                    "y": 0,
                    "w": 1,
                    "h": 1
                },
                {
                    "key": "d",
                    "x": 4,
                    "y": 1,
                    "w": 1,
                    "h": 1
                }
            ],
            "screen_x": 584.0,
            "screen_y": 755.0,
            "screen_width": 633.0,
            "screen_height": 263.0
        },
        {
            "width": 2,
            "height": 2,
            "actions": [
                {
                    "key": "a",
                    "x": 0,
                    "y": 0,
                    "w": 1,
                    "h": 1
                },
                {
                    "key": "d",
                    "x": 2,
                    "y": 1,
                    "w": 1,
                    "h": 1
                }
            ]
        }
    ]
}